slaf/__init__.py
slaf/cli.py
slaf/core/__init__.py
slaf/core/fragment_processor.py
slaf/core/query_optimizer.py
slaf/core/slaf.py
slaf/core/sparse_ops.py
slaf/data/__init__.py
slaf/data/chunked_reader.py
slaf/data/converter.py
slaf/data/dataset.py
slaf/data/utils.py
slaf/integrations/__init__.py
slaf/integrations/anndata.py
slaf/integrations/scanpy.py
slaf/ml/__init__.py
slaf/ml/aggregators.py
slaf/ml/dataloaders.py
slaf/ml/datasets.py
slaf/ml/samplers.py
slaf/ml/tiledb_dataloaders.py
slaf/ml/tokenizers.py
slafdb-0.3.1.dist-info/licenses/LICENSE
slafdb-0.3.1.dist-info/METADATA
slafdb-0.3.1.dist-info/WHEEL
slafdb-0.3.1.dist-info/entry_points.txt
slafdb-0.3.1.dist-info/top_level.txt
slafdb-0.3.1.dist-info/RECORD
