Metadata-Version: 2.4
Name: slafdb
Version: 0.3.1
Summary: Sparse Lazy Array Format - MVP for single-cell data
Author-email: Pavan Ramkumar <pavan.ramkumar@gmail.com>
License: Apache-2.0
Requires-Python: <3.14,>=3.10
License-File: LICENSE
Requires-Dist: pylance>=0.31.0
Requires-Dist: polars>=1.31.0
Requires-Dist: numpy>=2.2.0
Requires-Dist: pandas>=2.3.0
Requires-Dist: pyarrow>=20.0.0
Requires-Dist: scipy>=1.15.0
Requires-Dist: loguru>=0.7.0
Requires-Dist: scanpy>=1.11.2
Requires-Dist: h5py>=3.10.0
Requires-Dist: requests>=2.32.4
Requires-Dist: typer>=0.9.0
Requires-Dist: rich>=14.0.0
Requires-Dist: tqdm>=4.67.0
Requires-Dist: build>=1.2.2.post1
Requires-Dist: lancedb>=0.24.2
Requires-Dist: boto3>=1.40.10
Requires-Dist: smart-open[s3]>=7.4.1
Provides-Extra: ml
Requires-Dist: torch>=2.7.1; extra == "ml"
Requires-Dist: tiledb>=0.34.2; extra == "ml"
Requires-Dist: tiledbsoma>=1.17.1; extra == "ml"
Provides-Extra: advanced
Requires-Dist: igraph>=0.11.9; extra == "advanced"
Requires-Dist: leidenalg>=0.10.2; extra == "advanced"
Provides-Extra: dev
Requires-Dist: pytest>=8.0.0; extra == "dev"
Requires-Dist: ruff==0.12.2; extra == "dev"
Requires-Dist: mypy>=1.8.0; extra == "dev"
Requires-Dist: build>=1.0.0; extra == "dev"
Requires-Dist: twine>=4.0.0; extra == "dev"
Requires-Dist: marimo>=0.14.0; extra == "dev"
Requires-Dist: matplotlib>=3.10.0; extra == "dev"
Requires-Dist: seaborn>=0.13.0; extra == "dev"
Requires-Dist: psutil>=6.0.0; extra == "dev"
Requires-Dist: scvi-tools>=1.3.3; extra == "dev"
Requires-Dist: scdataset>=0.1.1; extra == "dev"
Requires-Dist: bionemo-scdl>=0.0.8; extra == "dev"
Requires-Dist: vortex-data>=0.33.2; extra == "dev"
Requires-Dist: datasets>=4.0.0; extra == "dev"
Requires-Dist: ray>=2.49.0; extra == "dev"
Requires-Dist: modal>=1.2.1; extra == "dev"
Requires-Dist: rclone-python>=0.1.23; extra == "dev"
Provides-Extra: docs
Requires-Dist: mkdocs>=1.5.0; extra == "docs"
Requires-Dist: mkdocs-material>=9.5.0; extra == "docs"
Requires-Dist: mkdocstrings[python]>=0.24.0; extra == "docs"
Requires-Dist: mkdocs-literate-nav>=0.6.0; extra == "docs"
Requires-Dist: mkdocs-section-index>=0.3.0; extra == "docs"
Requires-Dist: mkdocs-autorefs>=0.4.0; extra == "docs"
Requires-Dist: mkdocs-awesome-pages-plugin>=2.9.0; extra == "docs"
Requires-Dist: mkdocs-macros-plugin>=1.0.0; extra == "docs"
Requires-Dist: mkdocs-git-revision-date-localized-plugin>=1.2.0; extra == "docs"
Requires-Dist: mkdocs-git-authors-plugin>=0.8.0; extra == "docs"
Requires-Dist: mkdocs-minify-plugin>=0.7.0; extra == "docs"
Requires-Dist: mkdocs-redirects>=1.2.0; extra == "docs"
Provides-Extra: test
Requires-Dist: pytest>=8.0.0; extra == "test"
Requires-Dist: pytest-cov>=6.2.0; extra == "test"
Requires-Dist: coverage>=7.9.1; extra == "test"
Requires-Dist: scanpy>=1.11.2; extra == "test"
Requires-Dist: h5py>=3.10.0; extra == "test"
Requires-Dist: psutil>=6.0.0; extra == "test"
Requires-Dist: torch>=2.7.1; extra == "test"
Provides-Extra: full
Requires-Dist: slafdb[advanced,ml]; extra == "full"
Dynamic: license-file
